[
  {
    "id": 1,
    "pid": 1001,
    "ques": "Do you notice that you move around a lot when you sleep?",
    "doyouknow": "You can tell how active you are when you sleep by taking a look at your duvet before making your bed. A messier duvet usually means a more fidgety sleeper. ",
    "ansr": [
      {
        "mark": "A",
        "ans": "YES",
        "ansText": "I tend to move around a lot"
      },
      {
        "mark": "B",
        "ans": "NO",
        "ansText": "I useually waik to simmiler position"
      }
    ]
  },
  {
    "id": 2,
    "pid": 1002,
    "ques": "Do you often get to hot during the night?",
    "doyouknow": "Body temperature issues are one of the leading causes of sleep problems. Exercise and a warm bath one hour before bedtime can help.",
    "ansr": [
      {
        "mark": "A",
        "ans": "YES",
        "ansText": "I regulaly straggle to stay cool"
      },
      {
        "mark": "B",
        "ans": "NO",
        "ansText": "I never had issuse in heat"
      }
    ]
  },
  {
    "id": 3,
    "pid": 1003,
    "ques": "Are you aware any allergies you might have",
    "doyouknow": "Allergies are estimated to affect around one in five people in the UK. ",
    "ansr": [
      {
        "mark": "A",
        "ans": "YES",
        "ansText": "I tend to move around a lot"
      },
      {
        "mark": "B",
        "ans": "NO aware",
        "ansText": "Sometime have a runney,itchy nose or nasal congestion"
      },
      {
        "mark": "C",
        "ans": "NO",
        "ansText": "I dont have any allergies"
      }
    ]
  },
  {
    "id": 4,
    "pid": 1004,
    "ques": "In what position do you usually  sllep in?",
    "doyouknow": "Most people sleep on their sides, with 41% af adults choosing the fetal position as their favoured way to snooze. ",
    "ansr": [
      {
        "mark": "A",
        "ans": "My back or side",
        "ansText": ""
      },
      {
        "mark": "B",
        "ans": "My Front",
        "ansText": ""
      },
      {
        "mark": "C",
        "ans": "Cheng my position",
        "ansText": ""
      },
      {
        "mark": "D",
        "ans": "I,m not sure",
        "ansText": ""
      }
    ]
  }
]
